tests/__init__.py
tests/test_yatodol.py
yatodol/__init__.py
yatodol-0.0.1.dist-info/DESCRIPTION.rst
yatodol-0.0.1.dist-info/METADATA
yatodol-0.0.1.dist-info/RECORD
yatodol-0.0.1.dist-info/WHEEL
yatodol-0.0.1.dist-info/entry_points.txt
yatodol-0.0.1.dist-info/metadata.json
yatodol-0.0.1.dist-info/top_level.txt
